CONTRIBUTORS.txt
Changelog.rst
LICENSE
MANIFEST.in
README.rst
TODO
setup.cfg
setup.py
celery/__init__.py
celery/__main__.py
celery/_state.py
celery/beat.py
celery/bootsteps.py
celery/canvas.py
celery/exceptions.py
celery/five.py
celery/local.py
celery/platforms.py
celery/result.py
celery/schedules.py
celery/signals.py
celery/states.py
celery/app/__init__.py
celery/app/amqp.py
celery/app/annotations.py
celery/app/autoretry.py
celery/app/backends.py
celery/app/base.py
celery/app/builtins.py
celery/app/control.py
celery/app/defaults.py
celery/app/events.py
celery/app/log.py
celery/app/registry.py
celery/app/routes.py
celery/app/task.py
celery/app/trace.py
celery/app/utils.py
celery/apps/__init__.py
celery/apps/beat.py
celery/apps/multi.py
celery/apps/worker.py
celery/backends/__init__.py
celery/backends/amqp.py
celery/backends/arangodb.py
celery/backends/asynchronous.py
celery/backends/azureblockblob.py
celery/backends/base.py
celery/backends/cache.py
celery/backends/cassandra.py
celery/backends/consul.py
celery/backends/cosmosdbsql.py
celery/backends/couchbase.py
celery/backends/couchdb.py
celery/backends/dynamodb.py
celery/backends/elasticsearch.py
celery/backends/filesystem.py
celery/backends/mongodb.py
celery/backends/redis.py
celery/backends/riak.py
celery/backends/rpc.py
celery/backends/s3.py
celery/backends/database/__init__.py
celery/backends/database/models.py
celery/backends/database/session.py
celery/bin/__init__.py
celery/bin/amqp.py
celery/bin/base.py
celery/bin/beat.py
celery/bin/call.py
celery/bin/celery.py
celery/bin/celeryd_detach.py
celery/bin/control.py
celery/bin/events.py
celery/bin/graph.py
celery/bin/list.py
celery/bin/logtool.py
celery/bin/migrate.py
celery/bin/multi.py
celery/bin/purge.py
celery/bin/result.py
celery/bin/shell.py
celery/bin/upgrade.py
celery/bin/worker.py
celery/concurrency/__init__.py
celery/concurrency/asynpool.py
celery/concurrency/base.py
celery/concurrency/eventlet.py
celery/concurrency/gevent.py
celery_yywing.egg-info/PKG-INFO
celery_yywing.egg-info/SOURCES.txt
celery_yywing.egg-info/dependency_links.txt
celery_yywing.egg-info/entry_points.txt
celery_yywing.egg-info/not-zip-safe
celery_yywing.egg-info/requires.txt
celery_yywing.egg-info/top_level.txt
